ezbloom/__init__.py
ezbloom-0.0.1.dist-info/METADATA
ezbloom-0.0.1.dist-info/WHEEL
ezbloom-0.0.1.dist-info/top_level.txt
ezbloom-0.0.1.dist-info/RECORD
